README.md
setup.py
gruut_lang_fa/VERSION
gruut_lang_fa/__init__.py
gruut_lang_fa/lexicon.db
gruut_lang_fa.egg-info/PKG-INFO
gruut_lang_fa.egg-info/SOURCES.txt
gruut_lang_fa.egg-info/dependency_links.txt
gruut_lang_fa.egg-info/top_level.txt
gruut_lang_fa/espeak/lexicon.db
gruut_lang_fa/espeak/g2p/model.crf
gruut_lang_fa/g2p/model.crf
gruut_lang_fa/pos/postagger.model